adnexus/__init__.py
adnexus/config/__init__.py
adnexus/config/base_loader.py
adnexus/config/builtin.py
adnexus/config/helpers.py
adnexus/containers.py
adnexus/decorators.py
adnexus/exceptions.py
adnexus/integrations/__init__.py
adnexus/integrations/starlette.py
adnexus/markers.py
adnexus/providers.py
adnexus/warnings.py
adnexus/wrappers.py
adnexus-0.1.7.dist-info/LICENCE
adnexus-0.1.7.dist-info/METADATA
adnexus-0.1.7.dist-info/WHEEL
adnexus-0.1.7.dist-info/entry_points.txt
adnexus-0.1.7.dist-info/RECORD
