Metadata-Version: 2.1
Name: adnexus
Version: 0.1.7
Summary: Modern and fully typed declarative Di and IoC Framework
Home-page: https://github.com/Nictec/adnexus/
Author: nl
Author-email: nl@x-net.at
Requires-Python: >=3.11,<4.0
Classifier: Programming Language :: Python :: 3
Classifier: Programming Language :: Python :: 3.11
Classifier: Programming Language :: Python :: 3.12
Classifier: Programming Language :: Python :: 3.13
Requires-Dist: pydantic (>=2.6.4,<3.0.0)
Requires-Dist: pyyaml (>=6.0.1,<7.0.0)
Project-URL: Repository, https://github.com/Nictec/adnexus/
